CHANGES.txt
README.txt
buildout.cfg
setup.py
bootstrap/bootstrap.py
src/zc/__init__.py
src/zc.objectlog.egg-info/PKG-INFO
src/zc.objectlog.egg-info/SOURCES.txt
src/zc.objectlog.egg-info/dependency_links.txt
src/zc.objectlog.egg-info/namespace_packages.txt
src/zc.objectlog.egg-info/not-zip-safe
src/zc.objectlog.egg-info/requires.txt
src/zc.objectlog.egg-info/top_level.txt
src/zc/objectlog/__init__.py
src/zc/objectlog/configure.zcml
src/zc/objectlog/copier.py
src/zc/objectlog/copier.txt
src/zc/objectlog/i18n.py
src/zc/objectlog/interfaces.py
src/zc/objectlog/log.py
src/zc/objectlog/log.txt
src/zc/objectlog/tests.py
src/zc/objectlog/utils.py
src/zc/objectlog/browser/__init__.py
src/zc/objectlog/browser/configure.zcml
src/zc/objectlog/browser/default.pt
src/zc/objectlog/browser/interfaces.py
src/zc/objectlog/browser/log.py