Metadata-Version: 1.0
Name: zc.objectlog
Version: 0.2.2
Summary: a customizable log for a single object in Zope 3.
Home-page: UNKNOWN
Author: Gary Poster
Author-email: gary@zope.com
License: ZPL 2.1
Keywords: zope zope3 logging
Platform: UNKNOWN
